{
  "creds": {
    "noiseKey": {
      "private": {
        "type": "Buffer",
        "data": "oM98qPS7J5MLxZsHbljgwAqOnhbe/x5kMOh+FyoNfnI="
      },
      "public": {
        "type": "Buffer",
        "data": "2Q5WF6kPTwyW7vuyvbLDJ52SwN1wVzx7npPT0jlHvT0="
      }
    },
    "signedIdentityKey": {
      "private": {
        "type": "Buffer",
        "data": "qEVNcouOLKmF0thLnv7xbZ1LTKknJGravZDPWeAWzXo="
      },
      "public": {
        "type": "Buffer",
        "data": "RjxqRZRI94K314Ojk3gZmfvhCqBU3fad8DCV/rvpPiw="
      }
    },
    "signedPreKey": {
      "keyPair": {
        "private": {
          "type": "Buffer",
          "data": "+Pe7T9I4C+ziz08GJ6/SSnNfC3nVd3JKxvqptWzPjX8="
        },
        "public": {
          "type": "Buffer",
          "data": "lbVl+FdXGN1g5qpJMOISuy6xhKtznYrXeCUTuBHH1l0="
        }
      },
      "signature": {
        "type": "Buffer",
        "data": "9aiNW/lAhkIHxKvPN+BzRFZGwEscLaKVsqMrX5FSaijG+nEAw7qd43nQpVFXyzUfsETtuXyG1pJN3xKIMCKGAQ=="
      },
      "keyId": 1
    },
    "registrationId": 247,
    "advSecretKey": "zB3DQS7S/RaXdxa7J93vOWSn86f2Hjg0IPuNVemqP9w=",
    "processedHistoryMessages": [
      {
        "key": {
          "remoteJid": "6287739421476@s.whatsapp.net",
          "fromMe": true,
          "id": "E97F555EE3AB66EE50FE75AF34D19796"
        },
        "messageTimestamp": 1672037171
      },
      {
        "key": {
          "remoteJid": "6287739421476@s.whatsapp.net",
          "fromMe": true,
          "id": "E75D9F0E1F9D53AFD330267790AD6B5B"
        },
        "messageTimestamp": 1672037171
      },
      {
        "key": {
          "remoteJid": "6287739421476@s.whatsapp.net",
          "fromMe": true,
          "id": "CBFBAC2AA1BF3473A667BFFB5E7EC8CC"
        },
        "messageTimestamp": 1672037205
      }
    ],
    "nextPreKeyId": 31,
    "firstUnuploadedPreKeyId": 31,
    "accountSettings": {
      "unarchiveChats": false
    },
    "account": {
      "details": "CMuQntgFEK+GpZ0GGAE=",
      "accountSignatureKey": "0UiMNZ3OLp800QcQPR184fcTVdtY+hmkE0fHJS7jPUk=",
      "accountSignature": "7d7U7+Zp5cJeCtSXx/vxX3ZPxFz9cJAS4M89yiplpksH7Nuikt6lFgpv6lNCIPLCXmvjTRXkFZy8zG787NjXDg==",
      "deviceSignature": "NOH02cqyY9q5AsxuOBlwAiJuBeMLgSZj1XH4xyu7jZaaitdLF/IPdPbMmmMEzMI2e5ut5ZTW+aWjSakJqEvrBw=="
    },
    "me": {
      "id": "6287739421476:1@s.whatsapp.net",
      "name": "sunflower🌻"
    },
    "signalIdentities": [
      {
        "identifier": {
          "name": "6287739421476:1@s.whatsapp.net",
          "deviceId": 0
        },
        "identifierKey": {
          "type": "Buffer",
          "data": "BdFIjDWdzi6fNNEHED0dfOH3E1XbWPoZpBNHxyUu4z1J"
        }
      }
    ],
    "platform": "android",
    "lastAccountSyncTimestamp": 1672037168,
    "myAppStateKeyId": "AAAAALik"
  },
  "keys": {
    "preKeys": {
      "1": {
        "private": {
          "type": "Buffer",
          "data": "oHd6HIqW0xNw6tsYtSdbrDfpZMNefSnMFO3GjnweolA="
        },
        "public": {
          "type": "Buffer",
          "data": "cbNhXoyqZoUnqxxXRLCfCYZvzd97f0LodrAjQeLP5HU="
        }
      },
      "2": {
        "private": {
          "type": "Buffer",
          "data": "KEpKFtl3VVwpgf+f+NFe50fZDAb92kmOW41lVAZMNUY="
        },
        "public": {
          "type": "Buffer",
          "data": "cg7sspIvQFFiZmpLyyaiI/hfWErjfFRgloXErXIS6VQ="
        }
      },
      "3": {
        "private": {
          "type": "Buffer",
          "data": "GAjgbsESRTPKoDRdUDkJ3QD6mTc8UsW4LwCzC20j2Wo="
        },
        "public": {
          "type": "Buffer",
          "data": "j7uyqpjZesSjo8o7B84gt4kPcf2q15cDeN1f83SFhW0="
        }
      },
      "4": {
        "private": {
          "type": "Buffer",
          "data": "mI4RZ2PrexK5cr3zuOkCfFjChaTr22kcX6s9dCuYdVs="
        },
        "public": {
          "type": "Buffer",
          "data": "c5k6ZOoOcIG6pYKsaZ7yiuAhl9esgMDOVC0jSFxJJCY="
        }
      },
      "5": {
        "private": {
          "type": "Buffer",
          "data": "cHbOli4oSdrXQXWMZKFQ9uDsLDsizhaeSsHMX9Tn2Go="
        },
        "public": {
          "type": "Buffer",
          "data": "rXSFNgqK27JdnqR7/gLtp0C0PQ1OF9J3jxYBAzDkpAA="
        }
      },
      "6": {
        "private": {
          "type": "Buffer",
          "data": "oEQ2m1nFR3N1F443GuCYsJgAkFX9ecAKFSIrCcoFJWM="
        },
        "public": {
          "type": "Buffer",
          "data": "8fKYiMg0XL34LSgLIx1z0YuHG8snOgayKZb/4UBVRB0="
        }
      },
      "7": {
        "private": {
          "type": "Buffer",
          "data": "WJq9gtFfsWLRkU3vnyIHgUJjFwPxE1wxkCQzHlf2YG8="
        },
        "public": {
          "type": "Buffer",
          "data": "CjRp4hNE6H1hoypJHWTT59pb8Mp9tx6MNw/i5AcWnDA="
        }
      },
      "8": {
        "private": {
          "type": "Buffer",
          "data": "uDN6+nfPTVxioQ51sFS+ADh+Pxq66wp6ohXIITxXc04="
        },
        "public": {
          "type": "Buffer",
          "data": "/oQkUiYUA211VO31w3Ma/IRiA6lSWsWAjnbJCP4/MwA="
        }
      },
      "9": {
        "private": {
          "type": "Buffer",
          "data": "eJ8+mZPMx/C/HYI6sbjUgGjOv/CSg18gC5ltkOyUW3M="
        },
        "public": {
          "type": "Buffer",
          "data": "Nx0iemue1jkP3Z/AR0uhBy0rk6lcbnoY6pmxcK/C2yY="
        }
      },
      "10": {
        "private": {
          "type": "Buffer",
          "data": "yKLHtM8sUsRm2h7QsG34QM8nnVYiscoe+g5/Aete32U="
        },
        "public": {
          "type": "Buffer",
          "data": "ksRY11AOG3lwBRVg6G4+cL154yWm91skGTf++DYeGXM="
        }
      },
      "11": {
        "private": {
          "type": "Buffer",
          "data": "AF8XtPs1cqFLdNgQN2Gfm/kk5p0rUgZSqWXjVEuePlk="
        },
        "public": {
          "type": "Buffer",
          "data": "Vx0L5whaE0AYbu55lq0tUue0nOBFjeYnUi8CbPr5LW8="
        }
      },
      "12": {
        "private": {
          "type": "Buffer",
          "data": "UGXWj38Ah/3E5zHf3JU6Mf7mzJlw8Uol1cM5f2gTTVs="
        },
        "public": {
          "type": "Buffer",
          "data": "m3iX+uoh7205Lf+b7mfHC5XyEFzg5Xcl+ZirTWhf7VA="
        }
      },
      "13": {
        "private": {
          "type": "Buffer",
          "data": "qMFsP1uMSLm7u3sfntz9ozut2RIqXMESyu8z2HLUu0k="
        },
        "public": {
          "type": "Buffer",
          "data": "jUSpEksd9nAcx74su68VqkY1WNnorEbgrqa8n8/rUSQ="
        }
      },
      "14": {
        "private": {
          "type": "Buffer",
          "data": "aII5EoWDC6C9FEY3nJIvFeBg+2ULq2ZhhgYoE5cvi0A="
        },
        "public": {
          "type": "Buffer",
          "data": "8vCuCsrbwIE50LvAm9l5HiK408fR9n9MeiSbMN5GpAA="
        }
      },
      "15": null,
      "16": {
        "private": {
          "type": "Buffer",
          "data": "eHO5bouk/XEQLN19HvO7fcC41COc1MqnmWxpCrs6l2s="
        },
        "public": {
          "type": "Buffer",
          "data": "l52jMYlzS8X7fDuTianEK638wbFrp47xNFRGi8IZS0k="
        }
      },
      "17": {
        "private": {
          "type": "Buffer",
          "data": "KGzv8OU1eZlDZQcZGZlO1kavyVYScVzXRTZ2R6KPa3E="
        },
        "public": {
          "type": "Buffer",
          "data": "GiInH6dGjZUOLVYXqK+e7kWkQAx3UXjxTWRyW8A5BRA="
        }
      },
      "18": {
        "private": {
          "type": "Buffer",
          "data": "MGHvNjwGSLLah1Hcb2H0mwS5y1A07+8V5qg6RxG67k4="
        },
        "public": {
          "type": "Buffer",
          "data": "bPDLtrzjhjQDwWx5iwVpqNVYNkan19ZduXixuglfBVI="
        }
      },
      "19": {
        "private": {
          "type": "Buffer",
          "data": "QP/cn8hguDqKSy1999Y8Md7Dw9+fv+Nx35YDyca+UGY="
        },
        "public": {
          "type": "Buffer",
          "data": "/NJTOENFHp6786qI979FrcZ9YBHX6U4VFL/Jnt0pyjI="
        }
      },
      "20": {
        "private": {
          "type": "Buffer",
          "data": "0OZ0zSxW5hSQPwEYJgB6Sbw6Zlodz4NxmO2tbz1Sd0I="
        },
        "public": {
          "type": "Buffer",
          "data": "V2WtDb125IibtbxkxNmfO4KKO1lXT99A10RGbqcXEic="
        }
      },
      "21": {
        "private": {
          "type": "Buffer",
          "data": "mFcIOHWiULDCsCRiWAgZbWuke6PKW5ELQvo0ebN2N0g="
        },
        "public": {
          "type": "Buffer",
          "data": "yoL1RL0uCk4jn2MZVhMh8aaUtrmMHYDx4XYhj0ahXnE="
        }
      },
      "22": {
        "private": {
          "type": "Buffer",
          "data": "yGjgG6lwjVr4/fHhmluNf6j3op5B4qCSpXGZGv/aoEI="
        },
        "public": {
          "type": "Buffer",
          "data": "B5aAeIaY8S06hIybCY7k2RUrUfJ2yXrVlsiJYZQu70o="
        }
      },
      "23": {
        "private": {
          "type": "Buffer",
          "data": "mIFEscb+rG2I5dPp6IZ5QMWFwGntxTR0i+iMj0PXiW4="
        },
        "public": {
          "type": "Buffer",
          "data": "HLmDFRtfBfocloeGpY4sR62s9bROk10N0FYCbEwgRR0="
        }
      },
      "24": {
        "private": {
          "type": "Buffer",
          "data": "6FGm9y83743ehoSvITLVIcUZQnQ7J51Ua9UDle36UXw="
        },
        "public": {
          "type": "Buffer",
          "data": "GPZpsZrScgtOT3UK8BizlfFzaHTlOLFsCE/J2LHT7Bk="
        }
      },
      "25": {
        "private": {
          "type": "Buffer",
          "data": "KNoYIPnjJbjkAk//V6Q8umRHxNXKvVJ4CrHNdw3xfmE="
        },
        "public": {
          "type": "Buffer",
          "data": "CLQl3aUWdg6n9LEFx8WRxawd4sevO8g9axmRtHAxbm0="
        }
      },
      "26": {
        "private": {
          "type": "Buffer",
          "data": "wH3PGSdHoBQzrFJp7OwJf2Z3h3qBNm+A/PTw3Vl5EGw="
        },
        "public": {
          "type": "Buffer",
          "data": "J5alCINMphgnAhrFwb5MX21PHLY3pUZxWG9VoydUgg0="
        }
      },
      "27": {
        "private": {
          "type": "Buffer",
          "data": "ICuRWijjdLN3leRa2j/3VS230ZYHIs1MYnZ6pwzPumQ="
        },
        "public": {
          "type": "Buffer",
          "data": "VACjAfxPpQ7kncU9V6G98azQTAJK0HqYhNhoijPwT24="
        }
      },
      "28": {
        "private": {
          "type": "Buffer",
          "data": "gGQ39PUjM53YvJ3ArlQvsShoDxFrTyDmyupNBaozGWY="
        },
        "public": {
          "type": "Buffer",
          "data": "UJ0rWgh1YMf8z/RMYIplDknCcZSHWUY5UJnt/RrRrDg="
        }
      },
      "29": {
        "private": {
          "type": "Buffer",
          "data": "CAMufoW5xiOjabJgJ3l+W6PWcXLR6qORyX5IwGEO7F4="
        },
        "public": {
          "type": "Buffer",
          "data": "NNvHavVcLI1zgcx/jp6MUGmGyCLGetuxPPejLtLRaWk="
        }
      },
      "30": {
        "private": {
          "type": "Buffer",
          "data": "oPcGeLS3uZAZOUTXrIig8k1jjVzu+PzEz4XVoJX+rVw="
        },
        "public": {
          "type": "Buffer",
          "data": "CT15zbi50c9nO6/eXhY/sFFkxqI15/BeEMl7rTfaC3U="
        }
      }
    },
    "sessions": {
      "6287739421476.0": {
        "_sessions": {
          "BbboXjPDIwQ7pAAbQzz412VBvb2Lj1fCNQOZ7zTvVrov": {
            "registrationId": 1030025101,
            "currentRatchet": {
              "ephemeralKeyPair": {
                "pubKey": "Be2O3CFkletoqjEMezWgVBnoQ3d1AR42AOMJtBYkGAAk",
                "privKey": "eOAaXai4Gqhk6I+wtgjeGZ+ExOQWixdON5A+9Oscn2U="
              },
              "lastRemoteEphemeralKey": "BUKWq3m+niXRiWli/p2jLD78hwccNfjdO2EKH0Jvj6le",
              "previousCounter": 3,
              "rootKey": "Da6GcZGrQ5re+iIEymOTSGqVV0XUi3rFPr+wTN2RBoA="
            },
            "indexInfo": {
              "baseKey": "BbboXjPDIwQ7pAAbQzz412VBvb2Lj1fCNQOZ7zTvVrov",
              "baseKeyType": 2,
              "closed": -1,
              "used": 1672037205117,
              "created": 1672037169678,
              "remoteIdentityKey": "BdFIjDWdzi6fNNEHED0dfOH3E1XbWPoZpBNHxyUu4z1J"
            },
            "_chains": {
              "BV2L9QGjPl7j279tQAwDXGKas+YV66LB06kG5jDFRiBz": {
                "chainKey": {
                  "counter": 4
                },
                "chainType": 2,
                "messageKeys": {}
              },
              "BUKWq3m+niXRiWli/p2jLD78hwccNfjdO2EKH0Jvj6le": {
                "chainKey": {
                  "counter": 0,
                  "key": "qNx+stotvWPgXKSzrnQjM7FauM82rO0GNrjIz+MDuOY="
                },
                "chainType": 2,
                "messageKeys": {}
              },
              "Be2O3CFkletoqjEMezWgVBnoQ3d1AR42AOMJtBYkGAAk": {
                "chainKey": {
                  "counter": -1,
                  "key": "87YH36SXqBCHP/xOfItaaNtZAYp2qMLFWNQbccHY7zo="
                },
                "chainType": 1,
                "messageKeys": {}
              }
            }
          }
        },
        "version": "v1"
      },
      "77759599716:1.0": {
        "_sessions": {
          "BeIgZyRoIExtt1b5LBv/uGvsuzpvZJFpEHA9ZgOdGLhc": {
            "registrationId": 204,
            "currentRatchet": {
              "ephemeralKeyPair": {
                "pubKey": "BRhNZcECVDBNsL3hw6ZUMkwgJPg+Ho2HdwoYOrCYsBUO",
                "privKey": "MMuvDIz7NRjJUV9DMsSGYvn3IA+z5YW4S07o4qcavlI="
              },
              "lastRemoteEphemeralKey": "BRPt2CqiMPeLGbPmI+Qdn7NjmnHBuYE6q/IxBuLMJ2cB",
              "previousCounter": 0,
              "rootKey": "Ned+Q0ojuxQ/CYXTmiPNkJNG/Jj2CEYB0b95mVtg65w="
            },
            "indexInfo": {
              "baseKey": "BeIgZyRoIExtt1b5LBv/uGvsuzpvZJFpEHA9ZgOdGLhc",
              "baseKeyType": 1,
              "closed": 1672037175410,
              "used": 1672037175210,
              "created": 1672037175210,
              "remoteIdentityKey": "BR9iI2gk3L/ICEgphSntSyGHE+wun3Q66uuClogZAWZi"
            },
            "_chains": {
              "BRhNZcECVDBNsL3hw6ZUMkwgJPg+Ho2HdwoYOrCYsBUO": {
                "chainKey": {
                  "counter": 0,
                  "key": "9DKh6BdkNgtakutNDu8yGDKdLsutTeCBKUgF7kKIJfs="
                },
                "chainType": 1,
                "messageKeys": {}
              }
            },
            "pendingPreKey": {
              "signedKeyId": 1,
              "baseKey": "BeIgZyRoIExtt1b5LBv/uGvsuzpvZJFpEHA9ZgOdGLhc"
            }
          },
          "BXDXddtQZVZdnEHUp0/F07RRr6l3tyMggqB3x88B71A8": {
            "registrationId": 204,
            "currentRatchet": {
              "ephemeralKeyPair": {
                "pubKey": "BRTzV7l9YhNW6xqE1SOxhkVmyZeCpzr06XWYID+LsAEG",
                "privKey": "kLktNp9aROK/RZCJFXQMEfd6GuEIpygBb6DaukBmY1g="
              },
              "lastRemoteEphemeralKey": "BRPt2CqiMPeLGbPmI+Qdn7NjmnHBuYE6q/IxBuLMJ2cB",
              "previousCounter": 0,
              "rootKey": "1fLxaJaiOYy5VTUKxCUXCb1ueK9xEmiTCtJB+J9XTqs="
            },
            "indexInfo": {
              "baseKey": "BXDXddtQZVZdnEHUp0/F07RRr6l3tyMggqB3x88B71A8",
              "baseKeyType": 1,
              "closed": -1,
              "used": 1672037175357,
              "created": 1672037175357,
              "remoteIdentityKey": "BR9iI2gk3L/ICEgphSntSyGHE+wun3Q66uuClogZAWZi"
            },
            "_chains": {
              "BRTzV7l9YhNW6xqE1SOxhkVmyZeCpzr06XWYID+LsAEG": {
                "chainKey": {
                  "counter": 2,
                  "key": "jcc0NLXN38/i/wR8Ojfj6OVeVGzFgfV6XUWJls0MkHs="
                },
                "chainType": 1,
                "messageKeys": {}
              }
            },
            "pendingPreKey": {
              "signedKeyId": 1,
              "baseKey": "BXDXddtQZVZdnEHUp0/F07RRr6l3tyMggqB3x88B71A8"
            }
          }
        },
        "version": "v1"
      },
      "77759599716.0": {
        "_sessions": {
          "BZ/s+gS2MJpfx67gVu3ngCR3Pei3PjVdYd/7SqfkfLln": {
            "registrationId": 1141067035,
            "currentRatchet": {
              "ephemeralKeyPair": {
                "pubKey": "Bf/Pw+xX8mOVR+dMHBmIGvWf+fTm5++xn9Qqgtbk7gNR",
                "privKey": "+C6MU3li7vd7g9FMcw2XBDvkTbh6TIS8D/pQ+XX86lg="
              },
              "lastRemoteEphemeralKey": "BRB69Uo7kRQGjspnRvMPbPnTQltS1ZhZgn/+GOotAFF/",
              "previousCounter": 0,
              "rootKey": "E7KBulxGyK8pzIPOzfhxY10tCxXj2jO7iopOZSajvUI="
            },
            "indexInfo": {
              "baseKey": "BZ/s+gS2MJpfx67gVu3ngCR3Pei3PjVdYd/7SqfkfLln",
              "baseKeyType": 1,
              "closed": 1672037175429,
              "used": 1672037175212,
              "created": 1672037175212,
              "remoteIdentityKey": "BWWCRKNlgci3kZ0xC8Nuzcx3ll8Mm9lEZDRZjHpfgr5u"
            },
            "_chains": {
              "Bf/Pw+xX8mOVR+dMHBmIGvWf+fTm5++xn9Qqgtbk7gNR": {
                "chainKey": {
                  "counter": 0,
                  "key": "GxjJzjJ7lpozFGmc6/Rv6vKsxQWpicg7y5dSbCXBkRo="
                },
                "chainType": 1,
                "messageKeys": {}
              }
            },
            "pendingPreKey": {
              "signedKeyId": 2,
              "baseKey": "BZ/s+gS2MJpfx67gVu3ngCR3Pei3PjVdYd/7SqfkfLln",
              "preKeyId": 13663516
            }
          },
          "BYMG2aCPCXqQI2Ac6MY7W20EfQBQIQgI91VHEwLZTVgB": {
            "registrationId": 1141067035,
            "currentRatchet": {
              "ephemeralKeyPair": {
                "pubKey": "BbNbkS/hQWKdhxV6oSVpnIoRzVICGRi1Gl65v5hk/ZlU",
                "privKey": "yKR8GGiUNK0VxP0qlN2CH8/W80hFe9HOvSDmABN+T28="
              },
              "lastRemoteEphemeralKey": "BRB69Uo7kRQGjspnRvMPbPnTQltS1ZhZgn/+GOotAFF/",
              "previousCounter": 0,
              "rootKey": "Sqv0uU2eJdXiXp6T5fq/sVEQsXcWN0nt9G+8hdTb8Vg="
            },
            "indexInfo": {
              "baseKey": "BYMG2aCPCXqQI2Ac6MY7W20EfQBQIQgI91VHEwLZTVgB",
              "baseKeyType": 1,
              "closed": -1,
              "used": 1672037175364,
              "created": 1672037175364,
              "remoteIdentityKey": "BWWCRKNlgci3kZ0xC8Nuzcx3ll8Mm9lEZDRZjHpfgr5u"
            },
            "_chains": {
              "BbNbkS/hQWKdhxV6oSVpnIoRzVICGRi1Gl65v5hk/ZlU": {
                "chainKey": {
                  "counter": 2,
                  "key": "1we/cSiF9LQ9K2qnpEsetdXPjjfvrHQfX+ddqnXfjyw="
                },
                "chainType": 1,
                "messageKeys": {}
              }
            },
            "pendingPreKey": {
              "signedKeyId": 2,
              "baseKey": "BYMG2aCPCXqQI2Ac6MY7W20EfQBQIQgI91VHEwLZTVgB",
              "preKeyId": 13663623
            }
          }
        },
        "version": "v1"
      }
    },
    "appStateSyncKeys": {
      "AAAAALik": {
        "keyData": "TNfV25ndgUFNHWcBNI5khvo5fY1VZPt7dMJ5tQOkvQc=",
        "fingerprint": {
          "rawId": 1527220299,
          "currentIndex": 1,
          "deviceIndexes": [
            0,
            1
          ]
        },
        "timestamp": "1672037169688"
      }
    },
    "appStateVersions": {
      "critical_block": {
        "version": 1,
        "hash": {
          "type": "Buffer",
          "data": "Cx5ShCyOih7xfjx/Vlz4lcdMi0je/ZLqCJfSUdLJgKSBNb4+uZqcEb1pYvxCGCLg1YkX+yGAvZSl7Ckix/1MTxNzX1pw2soTrR/PlnVNuMa+hmvnme1FlCmOaRYFfnrZXJ19VPW8V2Rbev9wSsOm5CDRxvk/BInhTPxitRW2V8c="
        },
        "indexValueMap": {
          "Gokk9H59XkVy686bqh6m23rEUBPmh+1oUPC22Od+hBQ=": {
            "valueMac": {
              "type": "Buffer",
              "data": "tw+5i8ihRdgSCh0XVTNNnctMACn4ucv8oUclNrY2Nag="
            }
          },
          "M2XKrYHE6ZcVeHSOdapMg2gDTOp1460M42JqwyQW0ek=": {
            "valueMac": {
              "type": "Buffer",
              "data": "3RPvaZfW3uZlVsm+CgodJ6LqhLPTO9nCFaRpoxE+CIA="
            }
          }
        }
      },
      "regular": {
        "version": 1,
        "hash": {
          "type": "Buffer",
          "data": "P9w9wmOolf+7GQymhpAhk8cfmERMf8dV2xKH+3e67rGsTN6A0iW0kvUctpDotdWRe2w1UxbkJ26dBxNgL13FwKV4vhfZkIP+Oai46Ka9Ers6tDjhHsc/Gj+wEBUJiekOJH4KZvGTwgS+TMq/re7gcjBYtJE8nKosy+GQ1v62/ok="
        },
        "indexValueMap": {
          "EKWBT/uGQ5EAjmWAcPWNFKaxLsI/4/HTy3sZ6nqYYtQ=": {
            "valueMac": {
              "type": "Buffer",
              "data": "xW7dyQDKpwLPtePOqcOsbzUjOZXYoE4dlJSJohGwnE8="
            }
          }
        }
      },
      "critical_unblock_low": {
        "version": 1,
        "hash": {
          "type": "Buffer",
          "data": "0218CgvaBBi6gsKhBsaYNhazrOrj6Xcn5X2OiIzRmPByqCG4/h8X580LPAqF/P/QfhWcdBgIaajvWsl9oP0qN0gbzfmRuh9dlY2cJhYx/+tix6dHfLDrZWPmVbxXZXEhNKWrY6gnOVaIPOPvksr3cxWOMTQbvJ+O79+QBXGiwvc="
        },
        "indexValueMap": {
          "vNFX5PAG9jb1tNdsWRsEPNkUPmZuGFVYLFhXNgm5fdI=": {
            "valueMac": {
              "type": "Buffer",
              "data": "oSH9ZhX6rX4Idz1czoFc5bkMjA0D20UkPEsEhjUkc7M="
            }
          },
          "YmcSFLTVa9OckB4hD9NuNrS22i3k7rCwtEwdPdhsR2E=": {
            "valueMac": {
              "type": "Buffer",
              "data": "A0/jptRDbJcplC5P691ZDASAAbzy3lbaKPMTHRLQg4g="
            }
          },
          "cYTO9hntWRsuCpZ19rayJODpp9DtluU8eYyKrW8KcqA=": {
            "valueMac": {
              "type": "Buffer",
              "data": "LiVV0mx+2rhGrh/tpeOpWtZeGkYmJat96SyWsJQj2kg="
            }
          },
          "vxO5lTPwhRCFiZfuFLAdh3iccbSTAn+Xja2ZlPwNmj0=": {
            "valueMac": {
              "type": "Buffer",
              "data": "yzkoBPXY4+LwiRzWSyRUHOMv5FP/+Q63HNjomKvUBe8="
            }
          },
          "UzPptg2nJFucIdtJV+Qqk6i9t3bfPOe4/DBN5DS5V+g=": {
            "valueMac": {
              "type": "Buffer",
              "data": "UkcWROI5ajOsLfmS98gHBU5T8VmVmWDX1iF1bj5ieqM="
            }
          },
          "SXySOSJjEOxkOp0MotauZ4eiA0ErKYRVp/cmbInA5ig=": {
            "valueMac": {
              "type": "Buffer",
              "data": "TWCezx8yXuerse4GQasw9lh65hNzsTmmYIX8XgMnAHA="
            }
          },
          "6yUfi9UvUnnUgmOcFmUnu7RmJwg2fw26uJvJ92/gI1g=": {
            "valueMac": {
              "type": "Buffer",
              "data": "OwqpGQx4R/J0BtkqsusnYHgsgLoNBXbOoG4g3iECYXc="
            }
          },
          "coOAxpf6UflufOPaZor4lpCbFbWdoAAuM5vrSVTLH+A=": {
            "valueMac": {
              "type": "Buffer",
              "data": "h/s8c4lqtdtYnDiYmM4jdd6zwrx5Mmv00BkambP3lQM="
            }
          },
          "jeYB9Wz+5+1Fp19B/e7A2mw580WfZSQ30Rmme97edlE=": {
            "valueMac": {
              "type": "Buffer",
              "data": "kOAq/TjzVQ0Y7dg/07iuaYCcZAvs2Gw7JHg8ZOIv3qY="
            }
          },
          "LAu0URecTCKNTv4n3GUsUOHpq4i2NSsM4bBSisi7DQs=": {
            "valueMac": {
              "type": "Buffer",
              "data": "5IrO3YpIvMLDLQFuz6+GIHMZZ47cSdUzRT/edHddiAI="
            }
          },
          "1Y2PHEKEcu+ddautLAnz+rkMK/LzS9xOcefVFH0dl5A=": {
            "valueMac": {
              "type": "Buffer",
              "data": "HBn8lUiFMpv7mGfFIU8yuyHsrrPbGpcudCzi0iI3ajg="
            }
          },
          "tOol9E1h1mr4Y3SRDw/NRt7qk76OjJA0yNivMvk+B1A=": {
            "valueMac": {
              "type": "Buffer",
              "data": "vJ+rpQUJqyfPSjLgpAySE1gvnUtoJuYDVIVxJkGJMfM="
            }
          },
          "AphXfSrQnBOrOxOka3JmLNO2BJ5te+VUEFry7wtec34=": {
            "valueMac": {
              "type": "Buffer",
              "data": "A/O7YoZUXLo0GXLVNuPzMhENAhBHZFQFboFnvb+/XvM="
            }
          },
          "I+tftXp7CGY4iEczgPJ20tOX76NOAZA/lb20DOkMRrM=": {
            "valueMac": {
              "type": "Buffer",
              "data": "G3VAgvRiIoFroAdCpWuC/nAhLgDTMJOvR8jVsWOS3pQ="
            }
          },
          "3wIQ9RLYAkWNrisGdRV0LQ5KmeGYz/7RMSVlyG3f4oM=": {
            "valueMac": {
              "type": "Buffer",
              "data": "Oi892/mpmzUBl9XOzG8CMSGGf1JC11YlKadPCxGouis="
            }
          },
          "gMI6V69fKPWIdLJfIOZbumeN/dOxbJlRPoJDvZBLLsQ=": {
            "valueMac": {
              "type": "Buffer",
              "data": "ga7lPqegWk1Nq6xSSGNGIERX11bM//+tYTT/YNLE/PQ="
            }
          },
          "mODl4LhcaHmD5OCfj7uqg27+vMo2smAA7+x8/59au1U=": {
            "valueMac": {
              "type": "Buffer",
              "data": "8VNuh0cDNn5a+t3TtkWslHQfcKL/4ylImMe0IXrGBY8="
            }
          },
          "UIXBbH5glZJV4qehFb6XSGRshWrQZF2iYFurLeogiGE=": {
            "valueMac": {
              "type": "Buffer",
              "data": "skbMjy7xDA50iG+cnzVMA3MT/TgpHuaD9NdkO1DCSYQ="
            }
          },
          "oA2mAwvS2qNAADN9DZi3AKmODasopuSnUI/F86SE0wc=": {
            "valueMac": {
              "type": "Buffer",
              "data": "T1W4F1s2DewuQNG2KZ8tCKjmHWElKCqHKlWlQslfdh0="
            }
          },
          "18O/tCjUxafzZ+bcazEnneHGPFU/ZjfcgfVlSOU/tUM=": {
            "valueMac": {
              "type": "Buffer",
              "data": "WpTDvn/IjsASWM8HZGmQMVqtt97D+R0hglZifERxCe8="
            }
          },
          "oTqTTFff6fzLVXn4LRZAYUHgFiJPs0lm6NwlwuOnFYE=": {
            "valueMac": {
              "type": "Buffer",
              "data": "yjyOiWjtlh0eyszFS8DajgqFr8i5YvAZ1zKRs9MI8Hk="
            }
          },
          "mnkcdfaXBOYhgB3x97UOK6YzQ918rQ63AyXUU614lnE=": {
            "valueMac": {
              "type": "Buffer",
              "data": "iaxvnVW6QciNttBY2m081ldMsxx4e4a+iysLrzV4YXI="
            }
          },
          "0YN0KdtfEsEebyPRG2SpscDQrVL1uW+9FjrJ1BoHVQo=": {
            "valueMac": {
              "type": "Buffer",
              "data": "lyz16JFnfygEPpQljYQHqa8q8/kIIYRrKmgqPELRw/U="
            }
          },
          "s/jgf7uja4g3NZMEpSrorollKuT35i3Lpl2V97mzLkI=": {
            "valueMac": {
              "type": "Buffer",
              "data": "kUMibaLJkMKz2zzqhHtyWvZiV2p8XOLJCY+tCljuFj4="
            }
          },
          "1lx83bc7wmZ5WSIPvqe7TLQve3hqkdvQkx+y+2JFUMw=": {
            "valueMac": {
              "type": "Buffer",
              "data": "YTXLdzTf3EJt9ZdwIioNg49xT//yZDhAC8MA9ivhW4o="
            }
          },
          "Cr49vY6O6Y3UYvs+nEJOvJhNwQ9pCPLUxUJY9+yeKU4=": {
            "valueMac": {
              "type": "Buffer",
              "data": "WBJ8xqKPyX3vixnvZR6YQPzTUB2tmHAcUQG7SO399wY="
            }
          },
          "CLHFjOCv/kepVFcyx9ru7/EpuYDYkKDWU5VTxu5+ht0=": {
            "valueMac": {
              "type": "Buffer",
              "data": "a3e562cuyStIslQwgMrBaHTCKovdccEDKulOFFghseY="
            }
          },
          "Ia4neHxlW4wkTYI99ItX4ob0PlzTIHXdRMGWRjH7rNs=": {
            "valueMac": {
              "type": "Buffer",
              "data": "PUk5mWJxo6RwYWqBEualnDbR1o+OBQy75PVmkUhGd54="
            }
          },
          "9UliMYwnS9lS896GsjS1lBlkBgRLyHk62+vcq3zpJD0=": {
            "valueMac": {
              "type": "Buffer",
              "data": "4ldNWzquXoGmBMT47k1VdIdRivkzFJddtLGDsorNvy0="
            }
          },
          "2YtofzK4perIyAtcTYoFbVYNzfj/NDSOuDioYJJyRLc=": {
            "valueMac": {
              "type": "Buffer",
              "data": "jCV4wyTzbLDDVbVndThA3WwJbZwBcI/EsgANqxvDojY="
            }
          },
          "JyeLIYlzw+dyCaqUFaHK2i2bZF5eRNSPcgy2bGV//LE=": {
            "valueMac": {
              "type": "Buffer",
              "data": "bwOyYT7OImMMW1ZnJULz84mUHEL/lC+zaFjAv2OZA78="
            }
          },
          "60r4tFu3JLsJp70Lehyyq/VfNaWQB40q2STwDeuyVUY=": {
            "valueMac": {
              "type": "Buffer",
              "data": "fAon+uW+8d7F78XWOhOcSv6kIA9vLo6PnTVP0G56vcg="
            }
          },
          "tVqc9aOHfm5dEATaOhNfA3LBdvmcLlOiURmVc4IZJjM=": {
            "valueMac": {
              "type": "Buffer",
              "data": "pe455DMhL1nnKkV/3XVUyX0S6c+MoWwjApHhwcpMHE8="
            }
          },
          "+48J/bfyv1F1zaREbN+MapFuI4fddhySdOKkFZJ7kl0=": {
            "valueMac": {
              "type": "Buffer",
              "data": "SsYAa0zt07qvrUKymgQXaGuVME8dyaCc8GKoUVSxNNo="
            }
          },
          "x1JL07L6ddp2J7a1WckMreRvbzhZIMWlR2e2Gl189AM=": {
            "valueMac": {
              "type": "Buffer",
              "data": "e8ueNU0hUACy+1LAoVtzrS8DRW4ha+taydwzWTXosds="
            }
          },
          "GxjCfrm75uQSQJMStBkPe+OMCGBsKY9Dqi5qVfcFxHc=": {
            "valueMac": {
              "type": "Buffer",
              "data": "mPnCrM+xxxxsXfGARqBESIqBYHOnL6LzAnPsjPfw4x0="
            }
          },
          "3Zi/t6GRvqRMoYU+bom52dLivHRCQGZbCYQYtdEPJO0=": {
            "valueMac": {
              "type": "Buffer",
              "data": "P3yi36uhkgiQuHhQe0CNfFdbK/x64zI+5oPG/vyWKBI="
            }
          },
          "Hq0S9LO0KM840n+s46byjg8MMqUfZsZ3LYWKBlMVgEs=": {
            "valueMac": {
              "type": "Buffer",
              "data": "L3vBiibhHgcyZEMC1X/+Cnepzic6X3FDHzKpGZBk7vQ="
            }
          },
          "lO61czmOfWQ8t0jfcOUaBFeYbCwFm/sjwnVPB7dO+M8=": {
            "valueMac": {
              "type": "Buffer",
              "data": "wh9FFKNrtZUhqzWex4lcedLFhorpJ9BFHwJOC9TXAkU="
            }
          },
          "AitWPeDXexg9p6kw8nDdTWAQiWvzlZKhznVQAdoG16s=": {
            "valueMac": {
              "type": "Buffer",
              "data": "Xr0tWm1UHh2N73P/3wL+4+Hbt3ArbEaxXAmdMEa6D8s="
            }
          },
          "g1lOe0fCsgs3yowLHiiapU2IUB2Z17lPorMlmwAqhgM=": {
            "valueMac": {
              "type": "Buffer",
              "data": "Z+qBIBB62VV7Git3FL7Xmo+86JdYY8qnPFn44Y7XlTA="
            }
          },
          "b8KF9B+gel3899+OjVY65hb2z19DTS8gesUNfvdT16I=": {
            "valueMac": {
              "type": "Buffer",
              "data": "NdPJVsSlnipp62XZjMaOto78PTt5FiSo+jVO3YLI2jc="
            }
          },
          "EDTMx55OLJ0qtzay0bYEjckyGAnjJFqF8Kh2UzJo+rU=": {
            "valueMac": {
              "type": "Buffer",
              "data": "9YN2yztW0+t47ns+RqrS9UI+6c1PXDLj+/cAOFhOwP8="
            }
          },
          "En9AHDC/98KqCmo+oIHhBeSHqW45obFGpw66Myveq48=": {
            "valueMac": {
              "type": "Buffer",
              "data": "AYy1gta6jLaNUHKToKz3sxqc3jD6yFALzxL0aq4wlow="
            }
          },
          "lI9jSYx+SzwEjHp0tVI7xMJKXI3i2OTidizAR+eSYc0=": {
            "valueMac": {
              "type": "Buffer",
              "data": "jqITVP1TrHkVeURh7s7C77GKBFDe4GogWV1W372j5v0="
            }
          },
          "6kgCNzNs1NCbVycj5rNWJxRJngUL7P5p1wekYhL+7Dk=": {
            "valueMac": {
              "type": "Buffer",
              "data": "7Ggj2chrzRCVBxi/l75aXpD2lznM80MvhnJneduBsko="
            }
          },
          "hvPNi9nwLHEDnBYIjT4al7WztQX76jaQSqlswevC5iA=": {
            "valueMac": {
              "type": "Buffer",
              "data": "P3udp1AYlI15dQVg3+rFszfFm2uanzlDTp/hPOTBtbc="
            }
          },
          "CGfxJJmp6vLR4tODWwPXoLWzyrAC4NTVjdha4u27yV0=": {
            "valueMac": {
              "type": "Buffer",
              "data": "lzVE/UbYxlKuWngOK+UAnBaGVKzwuhLjVTMaKln0RRg="
            }
          },
          "z0nZ/0ucLGZkwFPZGk0Y36CrtPDWzCO2zL5e+Vdu4vQ=": {
            "valueMac": {
              "type": "Buffer",
              "data": "QycYjOAla1Y8lb1Vss9fBg81Zn3YtA8fRvlubFlI5pQ="
            }
          },
          "sv8xG0wvkCM4uX2I7fDtmlRDFKCGqV1PAwiwTAZ18Pg=": {
            "valueMac": {
              "type": "Buffer",
              "data": "tQSzC3UTgKaB9zKYha4nY/3G7neqZVoitnbnod/V5lQ="
            }
          },
          "hUsVyhmMBW7tcTwin9IH2sV2xxEwp1JRZDbs6FwnCOk=": {
            "valueMac": {
              "type": "Buffer",
              "data": "P8/lz3SnyTZ5lgRwZz7kl9jQzD81+9s3u0QkuL4INsU="
            }
          },
          "AypirmAeVLDasGVnlvxt9QDKLJRC7uhGnl0DPAp67F8=": {
            "valueMac": {
              "type": "Buffer",
              "data": "nEvMscoyeVo3g5CD/C8lU37QtgP6OpIe2AWOLZeNARM="
            }
          },
          "tNbZt+8iBCoEOiy1XN6RzpJQRmeIMBgSqnZ/UWd2osM=": {
            "valueMac": {
              "type": "Buffer",
              "data": "UaKE/k9p/EoNYuCfBq8H93xeqkgMvbLB8dXHOaB82jo="
            }
          },
          "aACHBawbS+NEY7Sm5gnRcdSt+y9CT2ihFO6DDACalTE=": {
            "valueMac": {
              "type": "Buffer",
              "data": "AowHaSXeZ3vSeUjpWbrP+4wmGsllB58v30npGVsx1Bk="
            }
          },
          "ePJft1m4d0bqdwMK4fR+WgHPTIn94lROPBqR1bUlQSs=": {
            "valueMac": {
              "type": "Buffer",
              "data": "vncy7Po6OhusRoD50lisbFeWvuvZyzD44W0YMJRS368="
            }
          },
          "sriU9rSNt/vMuJ0fPQl5nXdscR96iL/Rcrhi3b4Mt/A=": {
            "valueMac": {
              "type": "Buffer",
              "data": "29hPWGFmCOsAvDB7pKUV8BGwoy9upZEdF579sIPEm/w="
            }
          },
          "Oo3cZo6jw2R8FExG59gk0olBGYxhIkPRAj5rUmXW9BQ=": {
            "valueMac": {
              "type": "Buffer",
              "data": "ZKQdsFW/kQAn/aNSXjgk4aiUwHSvaaXpm1H0shqmEIo="
            }
          },
          "Ws6/Q3YMU6Tsv7+V80Ha8h1qplxR+BaHnUqDIj9S6fQ=": {
            "valueMac": {
              "type": "Buffer",
              "data": "1p7j+jAlks1Zmu+pVaareCoRwHx0PA+E2F4R9McoE4E="
            }
          },
          "Kbry1uHFsGvcmwz3EVLmtyDPDz1bBDdbPt2XdwJ1OdM=": {
            "valueMac": {
              "type": "Buffer",
              "data": "HZpvn+iCVGDJKzmVW9VDa/1TlMrgYllxRLTZ1k53iqg="
            }
          },
          "eD3t2qy4Ag0IcC5JnHA2QIhjAkjLhodkZDq9GSE+KgA=": {
            "valueMac": {
              "type": "Buffer",
              "data": "7z5F/7K9iFMQRe3JUd52Q2SotxRsPqGDJw40J9p5dxo="
            }
          },
          "E4RhpUXdQLD3cCBldfGBkRT78kgvnAKwkvRym+7xtt0=": {
            "valueMac": {
              "type": "Buffer",
              "data": "LypNJHEltJlXw+jeVUraZKTYBGLb2M/N0oESq5243kQ="
            }
          },
          "laeFv1ygLS+Lxd6wGxUmNPGNwy6WZKHP9BVsdyTcSPU=": {
            "valueMac": {
              "type": "Buffer",
              "data": "UEzwdMcf0IrS+NM6mckpJQXKXDHS/z8pOFavULVXKM8="
            }
          },
          "lpSgtE9YPVY+HCkCTzEOCUBTGzzUUYooZq5UkFwaUqw=": {
            "valueMac": {
              "type": "Buffer",
              "data": "/7XUtYFY/3JWw7PmOEYo1aYVwbku1cEJzFuVTIYERmA="
            }
          },
          "MKtiJVGcFHhBj0QlHJIofeEzCPilmpTVOThNbRFKRLA=": {
            "valueMac": {
              "type": "Buffer",
              "data": "2zFJ3vrLreO2PkojlQi2k83LAM44LmN195i01+BZ4os="
            }
          },
          "ucseSdaph1dHWI2Zb7s4Y8vlK63Dus9BiDeW0NeGDAo=": {
            "valueMac": {
              "type": "Buffer",
              "data": "ikiGyk4Mu8tX7mggDTwIIAfnmg6rGxS2Uas8yGkwSnE="
            }
          },
          "/w0TfKIUtGqlKgophJ6APHFlAYWSTbpVth4rGf1kRFI=": {
            "valueMac": {
              "type": "Buffer",
              "data": "ha8uSxU1eehA9a7wIh9VbHETDzTYmvFW291L2s7NZB4="
            }
          },
          "WivOjJFtUIbEdNXJuys9UVTxm15q0iD+V+aF06YArwQ=": {
            "valueMac": {
              "type": "Buffer",
              "data": "cLHyWN6K8is+pAayTqXeXNhp9tSG/4bVLVX4qRCBwOo="
            }
          },
          "LjbATDy5Bpzm21M4+Q18FGncHuRaog5foZZibdePDzY=": {
            "valueMac": {
              "type": "Buffer",
              "data": "/s8U+VZc14VO5mDXN9vKksSCubaw3NmSthr6srLGe5o="
            }
          },
          "G6Me8v5UOGK74uQR11LnkB2iYspVnU2uXLdBsRJbnqw=": {
            "valueMac": {
              "type": "Buffer",
              "data": "tL9r1w6y+vRhYnMGjux7Dt9Oyx9wGUCDc8NHm9y8wn0="
            }
          },
          "DfHzkuA3QUaJiJzFBzy/JKXpiqZ7yJZ/3OKpvQjPUiI=": {
            "valueMac": {
              "type": "Buffer",
              "data": "FnzDcL70o0+IgoVRAgFHyAuKOUCh9j0jPjpqatHp/6I="
            }
          },
          "15rv7JxXrL2S6/49PUvwSLWwud5ILJOqLYs0K2NtZS8=": {
            "valueMac": {
              "type": "Buffer",
              "data": "qLqKh2ZurDKAHDbljsQ4Lmh1o1+5EQTxyofgARRJHu4="
            }
          },
          "HKh37qL9bI6fmCiqEYatSqIKdw4lcZpsp9wvlDvIyOw=": {
            "valueMac": {
              "type": "Buffer",
              "data": "GdyU8GkeiZx9i8ec2pM+lAI5eXkfgzf/v7zwhyoJMuo="
            }
          },
          "nsSfGsHxQK7L3DohN9pwRVoUVpE1HEILi4sJ1FqhB64=": {
            "valueMac": {
              "type": "Buffer",
              "data": "49FDHitjjc/gt36CFynYnk0I8flBI/jO5DrweEqNx6Q="
            }
          },
          "JmOzffpE/ilovHq3hmnXJgMJiFYj8tpHa33Oao5R9q0=": {
            "valueMac": {
              "type": "Buffer",
              "data": "D11nHBgU+PEZAHrGElS2t7zGCv9ucIOrTqP3y9EGR7E="
            }
          },
          "sp4toluL1vEzzwMniBSqu7nyp3MIyRklUPBK89+S2GY=": {
            "valueMac": {
              "type": "Buffer",
              "data": "SHZfCF0On5gKPH0Tdaqs/BemyStHMC/Gck2ktmGeY/U="
            }
          },
          "IC6UBFlnb2DRZkkeQTI33hKgj7oOdneqFBJAy7RZkXY=": {
            "valueMac": {
              "type": "Buffer",
              "data": "3EKr1sF747eRqnIYn+E7DWdXmP/7VXfzDVlN/zkdvao="
            }
          },
          "JOsfxikHJSzzCIMR9FfGcFmCQpVAHT4EqVvrABnE8lI=": {
            "valueMac": {
              "type": "Buffer",
              "data": "ijnPgZQkpYTuk0Ai2ZHYA7erPmrtENpkEXGWyd4dr6M="
            }
          },
          "5rkP+UGLKivygdAwewTffs6go3bWRQ3DzgJQEaQiPdo=": {
            "valueMac": {
              "type": "Buffer",
              "data": "GSZqcNHQP+1i+Y7Z+GVcx8pFQ+4YFqGO17IM2NXfCNc="
            }
          },
          "QaThR8AoL9q6Ou4xxfqs1AoTzxafqGQSsF6xviB/e2c=": {
            "valueMac": {
              "type": "Buffer",
              "data": "cRKytgSYbNpHHDWgMgh4LxycyhIkg3zwkbO5BbGof3g="
            }
          },
          "5Imgs8wCnykWSHszUAZnTpWDz6QJ6fUtCshAE+r85rY=": {
            "valueMac": {
              "type": "Buffer",
              "data": "NXQsCysbFzHG8obToO0GFqsI5mV5kZw+vhsAs5qHfF0="
            }
          },
          "PeaL5/PrO3U3QPvfUh8ToJj9/g1RxnW5V3zmombHBGY=": {
            "valueMac": {
              "type": "Buffer",
              "data": "8I8b9egrgYQOvxSYSw9vNiY/KgoTAPaw5ghcJPXp/LU="
            }
          },
          "6ywb4Cuq4wwM9axtDXR9tPYyV0rJyTq5IFvIsIszBbw=": {
            "valueMac": {
              "type": "Buffer",
              "data": "6AsBGNafqKqLcKV2NmWNBdkLwTae7nqUfy8nP/f+uz0="
            }
          },
          "hKyr1JJ9uICZNXgDhmHL0uZ5+pTi5lCwm/oYUFja6NI=": {
            "valueMac": {
              "type": "Buffer",
              "data": "75VBo/topFcH9i/jObgdTx+mJLTjMC8xON8mT6qGdS4="
            }
          },
          "mHVvdhcy98q5HMPUsNMeSNo9LJocr+zWiib7guKY+Dw=": {
            "valueMac": {
              "type": "Buffer",
              "data": "nmmBLcYMw84HFVYcllPJO/q0xpLeMuNJZ0w5TriA1s8="
            }
          },
          "3zo4uOSu8jjj/2S3ojFYPypeeGSkvO4GSv5B3ZkBzzc=": {
            "valueMac": {
              "type": "Buffer",
              "data": "4S2LUnBILk9EyfCxDnx64op5NDvbAJz+BpNORVF55I8="
            }
          },
          "EzEHeNLJmpVGLFRpKY02VtYTYXYbCcKZmcIm2U7EVZc=": {
            "valueMac": {
              "type": "Buffer",
              "data": "gv6WQGF63kKcAfMk7/ZRyojN6/QRYoKf1sgwfhH//Vw="
            }
          },
          "dRW6jCIiAUPcFhGCCt5TlScT+yYUHftG6IWlUrZq57o=": {
            "valueMac": {
              "type": "Buffer",
              "data": "SbwEVP1Si8+v7fonhPGY1CvYbO0YVvOUa6/Uekb9NMQ="
            }
          },
          "Sxev9KUSZd986aPX4f8DodD/aSTZ1F7bp3xDCkQlRZs=": {
            "valueMac": {
              "type": "Buffer",
              "data": "v9isB76XTXxWZ68UYZFsh6Pm7N86DdHZoaD/wLCB96E="
            }
          },
          "Dx4XruYFUy8/XkcXXlI/Sd2Kt5SI5R6rMZnLs2p+zno=": {
            "valueMac": {
              "type": "Buffer",
              "data": "68V75AbAtS6v1VXXhPN5oYgMf5yyUvC6UMcLmFBwL8w="
            }
          },
          "26wmUuVWMUaKsMEQsfXiSzaLR2giQyDZtWgCOjiY0bU=": {
            "valueMac": {
              "type": "Buffer",
              "data": "oNgc5l36vToxik3geYR9eN9Y4OznzVkW7i3s9no+v2g="
            }
          },
          "r19I7O3eKeK+9YVWokY9pytzeD08GKXr518YS4Ae81k=": {
            "valueMac": {
              "type": "Buffer",
              "data": "oU+3giiccu3qLUbsEnr9DiFQw0JZeC2xOvkLfxGVM9M="
            }
          }
        }
      },
      "regular_high": {
        "version": 1,
        "hash": {
          "type": "Buffer",
          "data": "DNSFhCqJVUUBRAmbXok728F8Fcs952Z0SNjgaLsw1SDesNMhgVHIxjLkvxEPH/8rc036SMDSQvmkcRqKphUENilSfLxVapBmvAsG87HRREAt/Rl2EcEE5Y3OfN8pEdm5qNhFFy5dvfEaJfWb4rcWU3kJlZ2z0B5G9o9rQrcFrbc="
        },
        "indexValueMap": {
          "5K3pMMBSLrFqJBTzMjE9ennsF3jwYe+B2pwsNjBEJKg=": {
            "valueMac": {
              "type": "Buffer",
              "data": "w2zvGeybXrDIPBh5WQjy+xkk4lWaJpIKT64HQyG2SaY="
            }
          },
          "mUL2lJ3YlTj3iAMJre17YoefwKOv2ApfLyHFvVwaPRY=": {
            "valueMac": {
              "type": "Buffer",
              "data": "z8zuuxENlgRLWZPgGtvVdX/vrjskX0WzDQMWSUM0cY0="
            }
          }
        }
      },
      "regular_low": {
        "version": 1,
        "hash": {
          "type": "Buffer",
          "data": "es2oWB8DDu90QZZrb0rA/o2aPtnefeN0r1FiePmy7gggXSTSjEGIiqQrkKG/uz2cHkSZTvuX6ujnrOXUbKVVTgxpWTDJGY1jZctjEhF81AzI73T231fxzKxy75EmS96NdVgGgM/UOILnUQY6KQvcjm+SnjhElVtovAPCrR3DvK8="
        },
        "indexValueMap": {
          "oJTrWtRWmxyNmgaEvjgeNzrPNiJ1dzzBxkmi7lbysDI=": {
            "valueMac": {
              "type": "Buffer",
              "data": "XQBvzjZCpogwNaMo/to+F7u80sUJon5IvzSIvJBkAFU="
            }
          },
          "qKdhsW/2kxxTNgn3bdcT7d2klcPaSN5TAAq+nIFHBpY=": {
            "valueMac": {
              "type": "Buffer",
              "data": "RlbPv9oTgPqsHfrvKatqY0Pwf1YRVt0yLRoT+9i89ng="
            }
          }
        }
      }
    }
  }
}